django_admin_safe_login/__init__.py
django_admin_safe_login/admin.py
django_admin_safe_login/apps.py
django_admin_safe_login/forms.py
django_admin_safe_login/locale/zh_hans/LC_MESSAGES/django.mo
django_admin_safe_login/locale/zh_hans/LC_MESSAGES/django.po
django_admin_safe_login/migrations/__init__.py
django_admin_safe_login/static/django-admin-safe-login/css/django-admin-safe-login.css
django_admin_safe_login/static/django-admin-safe-login/js/django-admin-safe-login.js
django_admin_safe_login/templates/admin/login.html
django_admin_safe_login-0.3.7.dist-info/licenses/LICENSE
django_admin_safe_login-0.3.7.dist-info/METADATA
django_admin_safe_login-0.3.7.dist-info/WHEEL
django_admin_safe_login-0.3.7.dist-info/top_level.txt
django_admin_safe_login-0.3.7.dist-info/RECORD
