Metadata-Version: 2.4
Name: django-admin-safe-login
Version: 0.3.7
Summary: Add captcha field for django admin's login page.
Author: rRR0VrFP
Maintainer: rRR0VrFP
License: MIT
Keywords: django admin extentions,django admin safe login
Classifier: Development Status :: 5 - Production/Stable
Classifier: Intended Audience :: Developers
Classifier: Topic :: Software Development :: Libraries :: Python Modules
Classifier: License :: OSI Approved :: MIT License
Classifier: Programming Language :: Python :: 3
Classifier: Programming Language :: Python :: 3 :: Only
License-File: LICENSE
Requires-Dist: Django>=2.2.20
Requires-Dist: django-static-jquery3>=5.1.0
Requires-Dist: django-simple-captcha>=0.5.14
Requires-Dist: django-secure-password-input>=0.1.3
Requires-Dist: django-simple-tags>=0.6.0
Dynamic: author
Dynamic: classifier
Dynamic: description
Dynamic: description-content-type
Dynamic: keywords
Dynamic: license
Dynamic: license-file
Dynamic: maintainer
Dynamic: requires-dist
Dynamic: summary
